tdatasuite/__init__.py
tdatasuite/tdatasuite.py
tdatasuite-1.0.0.dist-info/METADATA
tdatasuite-1.0.0.dist-info/WHEEL
tdatasuite-1.0.0.dist-info/top_level.txt
tdatasuite-1.0.0.dist-info/RECORD
