Metadata-Version: 2.2
Name: tdatasuite
Version: 1.0.0
Summary: A toolkit for Telegram data collection and analytics
Home-page: https://github.com/ZentravaFlow/tdatasuite
Author: ZentravaFlow
Requires-Python: <=3.12.8
Requires-Dist: pandas==2.2.3
Requires-Dist: mtprotocrypt==1.2.6.5b0
Requires-Dist: kurigram==2.1.37
Dynamic: author
Dynamic: description
Dynamic: description-content-type
Dynamic: home-page
Dynamic: requires-dist
Dynamic: requires-python
Dynamic: summary
